{"meta":{"code":200,"requestId":"5b51d6d2f594df1e605a10c3"},"notifications":[{"type":"notificationTray","item":{"unreadCount":0}}],"response":{"photos":{"count":14,"items":[{"id":"52c8415811d234eead738876","createdAt":1388855640,"source":{"name":"Foursquare for iOS","url":"https:\/\/foursquare.com\/download\/#\/iphone"},"prefix":"https:\/\/igx.4sqi.net\/img\/general\/","suffix":"\/22648469_8Ti0o0wo_7AA-4CMDDiwwLCZIbhNn_t0HlCymd1tVe8.jpg","width":717,"height":959,"user":{"id":"22648469","firstName":"TOT XARXES","gender":"male","photo":{"prefix":"https:\/\/igx.4sqi.net\/img\/user\/","suffix":"\/22648469-2TCA1CX2VK02D4QW.jpg"}},"checkin":{"id":"52c84150498ef2d087ecf1ef","createdAt":1388855632,"type":"checkin","timeZoneOffset":60},"visibility":"public"},{"id":"52af0b5d11d2d721b6ee1d22","createdAt":1387203421,"source":{"name":"Foursquare for iOS","url":"https:\/\/foursquare.com\/download\/#\/iphone"},"prefix":"https:\/\/igx.4sqi.net\/img\/general\/","suffix":"\/22648469_B32EgiYx-teQ73JALDkMboG4911CEHKat7QhVwhx37Q.jpg","width":717,"height":959,"user":{"id":"22648469","firstName":"TOT XARXES","gender":"male","photo":{"prefix":"https:\/\/igx.4sqi.net\/img\/user\/","suffix":"\/22648469-2TCA1CX2VK02D4QW.jpg"}},"checkin":{"id":"52af0b56498efc4ee7ff5f88","createdAt":1387203414,"type":"checkin","timeZoneOffset":60},"visibility":"public"},{"id":"50584cb8e4b05809b0e176fe","createdAt":1347964088,"source":{"name":"Foursquare for iOS","url":"https:\/\/foursquare.com\/download\/#\/iphone"},"prefix":"https:\/\/igx.4sqi.net\/img\/general\/","suffix":"\/22648469_tR6QdShMWHKHJGZFEBESSEW1P_RsgDZQk5l3-w-QmpQ.jpg","width":537,"height":720,"user":{"id":"22648469","firstName":"TOT XARXES","gender":"male","photo":{"prefix":"https:\/\/igx.4sqi.net\/img\/user\/","suffix":"\/22648469-2TCA1CX2VK02D4QW.jpg"}},"visibility":"public"},{"id":"50584cb3e4b07e9d8a171ecc","createdAt":1347964083,"source":{"name":"Foursquare for iOS","url":"https:\/\/foursquare.com\/download\/#\/iphone"},"prefix":"https:\/\/igx.4sqi.net\/img\/general\/","suffix":"\/22648469_-YSOWX2RWZGwi5bfb_C6h87_lqPoGp6-Z8OZymXlQ40.jpg","width":537,"height":720,"user":{"id":"22648469","firstName":"TOT XARXES","gender":"male","photo":{"prefix":"https:\/\/igx.4sqi.net\/img\/user\/","suffix":"\/22648469-2TCA1CX2VK02D4QW.jpg"}},"visibility":"public"},{"id":"50584cade4b018504ac56594","createdAt":1347964077,"source":{"name":"Foursquare for iOS","url":"https:\/\/foursquare.com\/download\/#\/iphone"},"prefix":"https:\/\/igx.4sqi.net\/img\/general\/","suffix":"\/22648469_1CHmA7iWQgFPVtvn7VeUWTsIHflOYRaYL1J9Tgyng-U.jpg","width":537,"height":720,"user":{"id":"22648469","firstName":"TOT XARXES","gender":"male","photo":{"prefix":"https:\/\/igx.4sqi.net\/img\/user\/","suffix":"\/22648469-2TCA1CX2VK02D4QW.jpg"}},"visibility":"public"},{"id":"50584ca8e4b05e2ded4e4587","createdAt":1347964072,"source":{"name":"Foursquare for iOS","url":"https:\/\/foursquare.com\/download\/#\/iphone"},"prefix":"https:\/\/igx.4sqi.net\/img\/general\/","suffix":"\/22648469_xwZFcqGGHacrayLNklw_iW4U5rC9KvMKRG8c6ctsWyg.jpg","width":537,"height":720,"user":{"id":"22648469","firstName":"TOT XARXES","gender":"male","photo":{"prefix":"https:\/\/igx.4sqi.net\/img\/user\/","suffix":"\/22648469-2TCA1CX2VK02D4QW.jpg"}},"visibility":"public"},{"id":"50584ca3e4b0340eb4810745","createdAt":1347964067,"source":{"name":"Foursquare for iOS","url":"https:\/\/foursquare.com\/download\/#\/iphone"},"prefix":"https:\/\/igx.4sqi.net\/img\/general\/","suffix":"\/22648469_aAt0dfg5q_vu_q2zBOm0kkGncfQBk3mgq_mxf7jr4pw.jpg","width":537,"height":720,"user":{"id":"22648469","firstName":"TOT XARXES","gender":"male","photo":{"prefix":"https:\/\/igx.4sqi.net\/img\/user\/","suffix":"\/22648469-2TCA1CX2VK02D4QW.jpg"}},"visibility":"public"},{"id":"50584c9ee4b047cacfcc901a","createdAt":1347964062,"source":{"name":"Foursquare for iOS","url":"https:\/\/foursquare.com\/download\/#\/iphone"},"prefix":"https:\/\/igx.4sqi.net\/img\/general\/","suffix":"\/22648469_rpngx_ehJQQsN1zMQ8hYejXc5nItEP73y75bLMKnmys.jpg","width":537,"height":720,"user":{"id":"22648469","firstName":"TOT XARXES","gender":"male","photo":{"prefix":"https:\/\/igx.4sqi.net\/img\/user\/","suffix":"\/22648469-2TCA1CX2VK02D4QW.jpg"}},"visibility":"public"},{"id":"50584c99e4b008a6a917f292","createdAt":1347964057,"source":{"name":"Foursquare for iOS","url":"https:\/\/foursquare.com\/download\/#\/iphone"},"prefix":"https:\/\/igx.4sqi.net\/img\/general\/","suffix":"\/22648469_pGMzFrtmygTxLeonCkN1HEbVg0HgkBj2HXtezPE8dJk.jpg","width":537,"height":720,"user":{"id":"22648469","firstName":"TOT XARXES","gender":"male","photo":{"prefix":"https:\/\/igx.4sqi.net\/img\/user\/","suffix":"\/22648469-2TCA1CX2VK02D4QW.jpg"}},"visibility":"public"},{"id":"50584c94e4b0dd76082e272d","createdAt":1347964052,"source":{"name":"Foursquare for iOS","url":"https:\/\/foursquare.com\/download\/#\/iphone"},"prefix":"https:\/\/igx.4sqi.net\/img\/general\/","suffix":"\/22648469_nmhvkNE4MTx7Bkad9iDIsU9FHoXlFXYI-jfwoFOC8Lc.jpg","width":537,"height":720,"user":{"id":"22648469","firstName":"TOT XARXES","gender":"male","photo":{"prefix":"https:\/\/igx.4sqi.net\/img\/user\/","suffix":"\/22648469-2TCA1CX2VK02D4QW.jpg"}},"visibility":"public"},{"id":"50584c8fe4b0e54029e27a3a","createdAt":1347964047,"source":{"name":"Foursquare for iOS","url":"https:\/\/foursquare.com\/download\/#\/iphone"},"prefix":"https:\/\/igx.4sqi.net\/img\/general\/","suffix":"\/22648469_znlFRRCKqGIedwo21ihwWiWDZFlCUZE-z6qcn3m45Lk.jpg","width":537,"height":720,"user":{"id":"22648469","firstName":"TOT XARXES","gender":"male","photo":{"prefix":"https:\/\/igx.4sqi.net\/img\/user\/","suffix":"\/22648469-2TCA1CX2VK02D4QW.jpg"}},"visibility":"public"},{"id":"50584c8ae4b018f7e615616f","createdAt":1347964042,"source":{"name":"Foursquare for iOS","url":"https:\/\/foursquare.com\/download\/#\/iphone"},"prefix":"https:\/\/igx.4sqi.net\/img\/general\/","suffix":"\/22648469_jhTIOv3GFjBaTji82pMvWN26vUGiX_pbvuA64sS_kNI.jpg","width":537,"height":720,"user":{"id":"22648469","firstName":"TOT XARXES","gender":"male","photo":{"prefix":"https:\/\/igx.4sqi.net\/img\/user\/","suffix":"\/22648469-2TCA1CX2VK02D4QW.jpg"}},"visibility":"public"},{"id":"4fd7be7be4b0759f73c75b82","createdAt":1339539067,"source":{"name":"Foursquare for iOS","url":"https:\/\/foursquare.com\/download\/#\/iphone"},"prefix":"https:\/\/igx.4sqi.net\/img\/general\/","suffix":"\/GCt1-Asyzc5gW97sAwiGP2yDku1Zq0a4xC5VAq5Kbjk.jpg","width":537,"height":720,"user":{"id":"22652441","firstName":"Javi Nowell","gender":"male","photo":{"prefix":"https:\/\/igx.4sqi.net\/img\/user\/","suffix":"\/22652441-GX1AEMFLT31TYFKB.jpg"}},"checkin":{"id":"4fd7be67e4b050a3e5a08d1d","createdAt":1339539047,"type":"checkin","timeZoneOffset":120},"visibility":"public"},{"id":"4fcb34c8e4b0ee2f3a9d640b","createdAt":1338717384,"source":{"name":"Foursquare for Android","url":"https:\/\/foursquare.com\/download\/#\/android"},"prefix":"https:\/\/igx.4sqi.net\/img\/general\/","suffix":"\/Dtl0uIcek6JIcIb1p5hqyCUPmv6zuIbs3Oc6hesIdA0.jpg","width":720,"height":540,"user":{"id":"24759346","firstName":"Miriam","lastName":"Porciuncula","gender":"female","photo":{"prefix":"https:\/\/igx.4sqi.net\/img\/user\/","suffix":"\/T3J54EHZWTHG4APC.jpg"}},"visibility":"public"}],"dupesRemoved":0}}}