{"meta":{"code":200,"requestId":"5b34994f4434b9176c22054d"},"notifications":[{"type":"notificationTray","item":{"unreadCount":2}}],"response":{"user":{"id":"21394827","firstName":"Jordi","lastName":"Carulla","gender":"male","canonicalUrl":"https:\/\/foursquare.com\/d4rkpikka","photo":{"prefix":"https:\/\/igx.4sqi.net\/img\/user\/","suffix":"\/4TH5RGAXYZT0FJQI.jpg"},"friends":{"count":19,"groups":[{"type":"friends","name":"Mutual friends","count":0,"items":[]},{"type":"others","name":"Other friends","count":19,"items":[{"id":"83668964","firstName":"Tinoshi","lastName":"Kitazawa","gender":"male","photo":{"prefix":"https:\/\/igx.4sqi.net\/img\/user\/","suffix":"\/83668964-IZTIMES50XEDBGUO.jpg"},"tips":{"count":0},"lists":{"groups":[{"type":"created","count":2,"items":[]}]},"homeCity":"Turin, Piedmont","bio":"","contact":{"facebook":"1081936112"}},{"id":"16509430","firstName":"El Kabron Bali","lastName":"Iglesias","gender":"male","photo":{"prefix":"https:\/\/igx.4sqi.net\/img\/user\/","suffix":"\/16509430-BHQF2UL1Q0XOH4JW"},"tips":{"count":5},"lists":{"groups":[{"type":"created","count":2,"items":[]}]},"homeCity":"Kuta, Indonesia","bio":"Join us in El Kabron bali !!!!","contact":{"twitter":"elkabron","facebook":"612891248"}},{"id":"67211388","firstName":"Nan","lastName":"Doe","gender":"male","photo":{"prefix":"https:\/\/igx.4sqi.net\/img\/user\/","suffix":"\/DQMBQGUIJLHKJDHO.jpg"},"tips":{"count":2},"lists":{"groups":[{"type":"created","count":2,"items":[]}]},"homeCity":"Barcelona, 56","bio":"","contact":{}},{"id":"42263686","firstName":"Geri","gender":"male","photo":{"prefix":"https:\/\/igx.4sqi.net\/img\/user\/","suffix":"\/0MTGBUH4O4THPTOA.jpg"},"tips":{"count":0},"lists":{"groups":[{"type":"created","count":2,"items":[]}]},"homeCity":"Cataluña","bio":"","contact":{}},{"id":"36737454","firstName":"Roberto","lastName":"Quesada Lopez","gender":"male","photo":{"prefix":"https:\/\/igx.4sqi.net\/img\/user\/","suffix":"\/TZQL2DYP1KQ2WDCS.jpg"},"tips":{"count":0},"lists":{"groups":[{"type":"created","count":2,"items":[]}]},"homeCity":"Cataluña","bio":"","contact":{"facebook":"506003943"}},{"id":"12556978","firstName":"Eva","lastName":"SisDu","gender":"none","photo":{"prefix":"https:\/\/igx.4sqi.net\/img\/user\/","suffix":"\/14J0ALYFPPH0T53N.jpg"},"tips":{"count":0},"lists":{"groups":[{"type":"created","count":2,"items":[]}]},"homeCity":"Cervera, Espanya","bio":"","contact":{"facebook":"1422566659"}},{"id":"25621745","firstName":"Josep","lastName":"Gaspar","gender":"male","photo":{"prefix":"https:\/\/igx.4sqi.net\/img\/user\/","suffix":"\/IGD0U3TBISF13DZJ.jpg"},"tips":{"count":4},"lists":{"groups":[{"type":"created","count":4,"items":[]}]},"homeCity":"Andalucía","bio":"","contact":{"facebook":"754247052"}},{"id":"5667453","firstName":"Angel","gender":"male","photo":{"prefix":"https:\/\/igx.4sqi.net\/img\/user\/","suffix":"\/blank_boy.png","default":true},"tips":{"count":6},"lists":{"groups":[{"type":"created","count":5,"items":[]}]},"homeCity":"Terrassa, Espanya","bio":"","contact":{}},{"id":"65790536","firstName":"Piku","lastName":"Piku","gender":"male","photo":{"prefix":"https:\/\/igx.4sqi.net\/img\/user\/","suffix":"\/blank_boy.png","default":true},"tips":{"count":0},"lists":{"groups":[{"type":"created","count":2,"items":[]}]},"homeCity":"","bio":"","contact":{"facebook":"1353305625"}},{"id":"43465295","firstName":"Poti","lastName":"Poti","gender":"male","photo":{"prefix":"https:\/\/igx.4sqi.net\/img\/user\/","suffix":"\/blank_boy.png","default":true},"tips":{"count":0},"lists":{"groups":[{"type":"created","count":2,"items":[]}]},"homeCity":"Cataluña","bio":"","contact":{"facebook":"1197814541"}}]}]},"tips":{"count":2},"homeCity":"Cataluña","bio":"","contact":{"twitter":"d4rkpikka","facebook":"1631943763"},"photos":{"count":3,"items":[{"id":"4f5676f3e4b00dc27dcd26b3","createdAt":1331066611,"source":{"name":"Foursquare for iOS","url":"https:\/\/foursquare.com\/download\/#\/iphone"},"prefix":"https:\/\/igx.4sqi.net\/img\/general\/","suffix":"\/aHHvxmZVxXiqwbrAC-CXYw_2BIUDZzi1dLgkXFizMOw.jpg","width":540,"height":720,"visibility":"public","venue":{"id":"4bd6a196637ba5939279f870","name":"Clot de la Mel","contact":{},"location":{"address":"C. Andrade, 40","lat":41.411924240822486,"lng":2.1947014331817627,"labeledLatLngs":[{"label":"display","lat":41.411924240822486,"lng":2.1947014331817627}],"postalCode":"08018","cc":"ES","city":"Barcelona","state":"Cataluña","country":"España","formattedAddress":["C. Andrade, 40","08018 Barcelona Cataluña","España"]},"categories":[{"id":"4bf58dd8d48988d163941735","name":"Park","pluralName":"Parks","shortName":"Park","icon":{"prefix":"https:\/\/ss3.4sqi.net\/img\/categories_v2\/parks_outdoors\/park_","suffix":".png"},"primary":true}],"verified":false,"stats":{"tipCount":1,"usersCount":246,"checkinsCount":781},"like":false,"beenHere":{"lastCheckinExpiredAt":0}}}]},"checkinPings":"off","pings":false,"type":"user","mayorships":{"count":0,"items":[]},"checkins":{"count":264,"items":[]},"lists":{"count":6,"groups":[{"type":"created","count":0,"items":[]},{"type":"followed","count":4,"items":[]},{"type":"yours","count":2,"items":[{"id":"21394827\/todos","name":"Jordi's Saved Places","description":"","type":"todos","editable":false,"public":true,"collaborative":false,"url":"\/d4rkpikka\/list\/todos","canonicalUrl":"https:\/\/foursquare.com\/d4rkpikka\/list\/todos","listItems":{"count":7}},{"id":"21394827\/venuelikes","name":"Jordi\u2019s Liked Places","description":"","type":"likes","editable":false,"public":true,"collaborative":false,"url":"\/d4rkpikka\/list\/venuelikes","canonicalUrl":"https:\/\/foursquare.com\/d4rkpikka\/list\/venuelikes","listItems":{"count":0}}]}]},"blockedStatus":"none","lenses":[]}}}