{"meta":{"code":200,"requestId":"5b3190fe4c1f672123d3b6f5"},"notifications":[{"type":"notificationTray","item":{"unreadCount":0}}],"response":{"user":{"id":"27667527","firstName":"lady","gender":"none","canonicalUrl":"https:\/\/foursquare.com\/user\/27667527","photo":{"prefix":"https:\/\/igx.4sqi.net\/img\/user\/","suffix":"\/blank_boy.png","default":true},"friends":{"count":0,"groups":[{"type":"friends","name":"Mutual friends","count":0,"items":[]},{"type":"others","name":"Other friends","count":0,"items":[]}]},"tips":{"count":1},"homeCity":"Cataluña","bio":"","contact":{},"photos":{"count":5,"items":[{"id":"506b5bbee4b02bda7fc553f6","createdAt":1349213118,"source":{"name":"Foursquare for Android","url":"https:\/\/foursquare.com\/download\/#\/android"},"prefix":"https:\/\/igx.4sqi.net\/img\/general\/","suffix":"\/27667527_Ph_RcEwYS_ochvz2X1RYtZHA6yi6amwPr_Y4ko6fGoU.jpg","width":540,"height":720,"visibility":"public","venue":{"id":"4cc970714650a35d814d8e1e","name":"Racó del Taulat","contact":{},"location":{"address":"Taulat, 44","lat":41.399551186555605,"lng":2.205853717247403,"labeledLatLngs":[{"label":"display","lat":41.399551186555605,"lng":2.205853717247403}],"postalCode":"08005","cc":"ES","city":"Barcelona","state":"Cataluña","country":"España","formattedAddress":["Taulat, 44","08005 Barcelona Cataluña"]},"categories":[{"id":"4bf58dd8d48988d1c0941735","name":"Mediterranean Restaurant","pluralName":"Mediterranean Restaurants","shortName":"Mediterranean","icon":{"prefix":"https:\/\/ss3.4sqi.net\/img\/categories_v2\/food\/mediterranean_","suffix":".png"},"primary":true}],"verified":false,"stats":{"tipCount":9,"usersCount":78,"checkinsCount":810},"like":false,"allowMenuUrlEdit":true,"beenHere":{"lastCheckinExpiredAt":0}},"tip":{"id":"506b5bbce4b061f770131a36","createdAt":1349213116,"text":"Mesa exquisita","type":"user","canonicalUrl":"https:\/\/foursquare.com\/item\/506b5bbce4b061f770131a36","likes":{"count":0,"groups":[]},"like":false,"logView":true,"agreeCount":0,"disagreeCount":0,"todo":{"count":0}}}]},"checkinPings":"off","pings":false,"type":"user","mayorships":{"count":0,"items":[]},"checkins":{"count":0,"items":[]},"lists":{"count":2,"groups":[{"type":"created","count":0,"items":[]},{"type":"followed","count":0,"items":[]},{"type":"yours","count":2,"items":[{"id":"27667527\/todos","name":"lady's Saved Places","description":"","type":"todos","editable":false,"public":true,"collaborative":false,"url":"\/user\/27667527\/list\/todos","canonicalUrl":"https:\/\/foursquare.com\/user\/27667527\/list\/todos","listItems":{"count":0}},{"id":"27667527\/venuelikes","name":"lady\u2019s Liked Places","description":"","type":"likes","editable":false,"public":true,"collaborative":false,"url":"\/user\/27667527\/list\/venuelikes","canonicalUrl":"https:\/\/foursquare.com\/user\/27667527\/list\/venuelikes","listItems":{"count":0}}]}]},"blockedStatus":"none","lenses":[]}}}