{"meta":{"code":200,"requestId":"5b351d09db04f5137690ab61"},"notifications":[{"type":"notificationTray","item":{"unreadCount":2}}],"response":{"user":{"id":"39662355","firstName":"Bruno","lastName":"Aldrufeu","gender":"male","canonicalUrl":"https:\/\/foursquare.com\/bobtainer","photo":{"prefix":"https:\/\/igx.4sqi.net\/img\/user\/","suffix":"\/G0MCH1GJLNEF4ACT.jpg"},"friends":{"count":15,"groups":[{"type":"friends","name":"Mutual friends","count":0,"items":[]},{"type":"others","name":"Other friends","count":15,"items":[{"id":"66473263","firstName":"Julio","lastName":"Pumarol","gender":"male","photo":{"prefix":"https:\/\/igx.4sqi.net\/img\/user\/","suffix":"\/5W1VM1LIAT00HQOR.jpg"},"tips":{"count":8},"lists":{"groups":[{"type":"created","count":2,"items":[]}]},"homeCity":"Ávila","bio":"","contact":{"facebook":"574661540"}},{"id":"64724035","firstName":"Sergi","lastName":"Garcia Barqueros","gender":"male","photo":{"prefix":"https:\/\/igx.4sqi.net\/img\/user\/","suffix":"\/U3NGFZI4YZHTNZNO.jpg"},"tips":{"count":0},"lists":{"groups":[{"type":"created","count":2,"items":[]}]},"homeCity":"Barcelona, 56","bio":"","contact":{"facebook":"1462741578"}},{"id":"64004620","firstName":"Laia","lastName":"Codo","gender":"female","photo":{"prefix":"https:\/\/igx.4sqi.net\/img\/user\/","suffix":"\/64004620-3SOSIQQNU3QFNK5V.jpg"},"tips":{"count":9},"lists":{"groups":[{"type":"created","count":4,"items":[]}]},"homeCity":"Barcelona, 56","bio":"","contact":{"facebook":"1387981339"}},{"id":"31577052","firstName":"Edu","gender":"male","photo":{"prefix":"https:\/\/igx.4sqi.net\/img\/user\/","suffix":"\/A2DQPG5R1I4ZSPZF.jpg"},"tips":{"count":14},"lists":{"groups":[{"type":"created","count":2,"items":[]}]},"homeCity":"Cataluña","bio":"","contact":{"facebook":"100001958412069"}},{"id":"51668202","firstName":"Nuria","lastName":"Gimenez","gender":"female","photo":{"prefix":"https:\/\/igx.4sqi.net\/img\/user\/","suffix":"\/FFWTCAERSDPU4HWA.jpg"},"tips":{"count":1},"lists":{"groups":[{"type":"created","count":2,"items":[]}]},"homeCity":"Barcelona, 56","bio":"","contact":{"twitter":"nurbcn77","facebook":"1444102417"}},{"id":"6845474","firstName":"Andres","lastName":"Garcia","gender":"male","photo":{"prefix":"https:\/\/igx.4sqi.net\/img\/user\/","suffix":"\/6845474-4A2VZYRP3A5ILAUA.jpg"},"tips":{"count":1},"lists":{"groups":[{"type":"created","count":2,"items":[]}]},"homeCity":"Barcelona, Espanya","bio":"","contact":{"twitter":"agarcime","facebook":"1269497711"}},{"id":"10976178","firstName":"Nicolás","lastName":"Madrid Castellano","gender":"male","photo":{"prefix":"https:\/\/igx.4sqi.net\/img\/user\/","suffix":"\/10976178-RTZ3THXAPI3OTCXT.jpg"},"tips":{"count":37},"lists":{"groups":[{"type":"created","count":6,"items":[]}]},"homeCity":"Barcelona, Espanya","bio":"","contact":{"facebook":"10203634223846026"}},{"id":"48783283","firstName":"Alexandre","lastName":"Ruzafa","gender":"male","photo":{"prefix":"https:\/\/igx.4sqi.net\/img\/user\/","suffix":"\/T0MOPWS2UK02P4O1.jpg"},"tips":{"count":0},"lists":{"groups":[{"type":"created","count":2,"items":[]}]},"homeCity":"Cataluña","bio":"","contact":{"facebook":"10155152625839816"}},{"id":"300361","firstName":"Carlos","lastName":"Cabezas","gender":"male","photo":{"prefix":"https:\/\/igx.4sqi.net\/img\/user\/","suffix":"\/0WVGVEU5CZE5NNJQ.png"},"tips":{"count":2},"lists":{"groups":[{"type":"created","count":3,"items":[]}]},"homeCity":"Barcelona, Spain","bio":"Tras mi faceta de hijo de puta sin corazón se esconde una persona formal y educad... ¡JAJA! ¡UN NIÑO EN SILLA DE RUEDAS! ¡QUÉ COSA MÁS FEA!","contact":{"twitter":"r0uzic","facebook":"684512557"}},{"id":"39204300","firstName":"Sheila","lastName":"Planas","gender":"female","photo":{"prefix":"https:\/\/igx.4sqi.net\/img\/user\/","suffix":"\/1QST0T34HCMVGUFP.jpg"},"tips":{"count":0},"lists":{"groups":[{"type":"created","count":2,"items":[]}]},"homeCity":"New York, NY","bio":"","contact":{"facebook":"784578116"}}]}]},"tips":{"count":2},"homeCity":"Cataluña","bio":"","contact":{"twitter":"bobtainer"},"photos":{"count":6,"items":[{"id":"50a0be9ee4b03f3cc35772f2","createdAt":1352711838,"source":{"name":"Foursquare for iOS","url":"https:\/\/foursquare.com\/download\/#\/iphone"},"prefix":"https:\/\/igx.4sqi.net\/img\/general\/","suffix":"\/39662355_vQFB0J8BMma6yf7sWqPJzZIoaB9oEhZ89Uw5loH_Cfw.jpg","width":537,"height":720,"visibility":"public","venue":{"id":"4b9d386cf964a5209e9a36e3","name":"RENFE Estación de Calatayud","contact":{"twitter":"adif_es"},"location":{"address":"Plaza de la Estación, s\/n","lat":41.34680132935116,"lng":-1.6385733051322606,"labeledLatLngs":[{"label":"display","lat":41.34680132935116,"lng":-1.6385733051322606}],"postalCode":"50300","cc":"ES","city":"Calatayud","state":"Aragón","country":"España","formattedAddress":["Plaza de la Estación, s\/n","50300 Calatayud Aragón","España"]},"categories":[{"id":"4bf58dd8d48988d129951735","name":"Train Station","pluralName":"Train Stations","shortName":"Train Station","icon":{"prefix":"https:\/\/ss3.4sqi.net\/img\/categories_v2\/travel\/trainstation_","suffix":".png"},"primary":true}],"verified":false,"stats":{"tipCount":6,"usersCount":1014,"checkinsCount":2210},"like":false,"beenHere":{"lastCheckinExpiredAt":0}},"tip":{"id":"50a0be90e4b076197d4f6d0a","createdAt":1352711824,"text":"Calatayud. Y pròxima parada: Madrid","type":"user","canonicalUrl":"https:\/\/foursquare.com\/item\/50a0be90e4b076197d4f6d0a","likes":{"count":2,"groups":[{"type":"others","count":2,"items":[{"id":"20445508","firstName":"Jorge","lastName":"Valera","gender":"male","photo":{"prefix":"https:\/\/igx.4sqi.net\/img\/user\/","suffix":"\/ZIP5OHYF5ZDMYQY4.jpg"}},{"id":"28388373","firstName":"Yajaira","lastName":"Rondón","gender":"female","photo":{"prefix":"https:\/\/igx.4sqi.net\/img\/user\/","suffix":"\/VQUEIAKLY5U0TRDV.jpg"}}]}],"summary":"2 likes"},"like":false,"logView":true,"agreeCount":2,"disagreeCount":0,"todo":{"count":0}}}]},"checkinPings":"off","pings":false,"type":"user","mayorships":{"count":0,"items":[]},"checkins":{"count":92,"items":[]},"lists":{"count":2,"groups":[{"type":"created","count":0,"items":[]},{"type":"followed","count":0,"items":[]},{"type":"yours","count":2,"items":[{"id":"39662355\/todos","name":"Bruno's Saved Places","description":"","type":"todos","editable":false,"public":true,"collaborative":false,"url":"\/bobtainer\/list\/todos","canonicalUrl":"https:\/\/foursquare.com\/bobtainer\/list\/todos","listItems":{"count":1}},{"id":"39662355\/venuelikes","name":"Bruno\u2019s Liked Places","description":"","type":"likes","editable":false,"public":true,"collaborative":false,"url":"\/bobtainer\/list\/venuelikes","canonicalUrl":"https:\/\/foursquare.com\/bobtainer\/list\/venuelikes","listItems":{"count":0}}]}]},"blockedStatus":"none","lenses":[]}}}