{"meta":{"code":200,"requestId":"5b23ca6b9fb6b7361fe9d3a5"},"notifications":[{"type":"notificationTray","item":{"unreadCount":0}}],"response":{"user":{"id":"44772003","firstName":"Marta","lastName":"Fernandez","gender":"female","canonicalUrl":"https:\/\/foursquare.com\/user\/44772003","photo":{"prefix":"https:\/\/igx.4sqi.net\/img\/user\/","suffix":"\/ITE2JEKRC0VKF00Z.jpg"},"friends":{"count":10,"groups":[{"type":"friends","name":"Mutual friends","count":0,"items":[]},{"type":"others","name":"Other friends","count":10,"items":[{"id":"14212093","firstName":"Fernando","lastName":"Moreno","gender":"none","photo":{"prefix":"https:\/\/igx.4sqi.net\/img\/user\/","suffix":"\/54PU2ABCB1XFGZVH.jpg"},"tips":{"count":0},"lists":{"groups":[{"type":"created","count":2,"items":[]}]},"homeCity":"Terrassa, Espanya","bio":"","contact":{"facebook":"1280797482"}},{"id":"60445063","firstName":"Albert","lastName":"Giménez","gender":"male","photo":{"prefix":"https:\/\/igx.4sqi.net\/img\/user\/","suffix":"\/C03OTEC1VP44Y0OA.jpg"},"tips":{"count":1},"lists":{"groups":[{"type":"created","count":2,"items":[]}]},"homeCity":"Sabadell, ","bio":"","contact":{"twitter":"thegimenees","facebook":"100006161760587"}},{"id":"53374229","firstName":"Joseph","lastName":"Segarra","gender":"male","photo":{"prefix":"https:\/\/igx.4sqi.net\/img\/user\/","suffix":"\/53374229-1YHT1A2LVRMNVTGB.jpg"},"tips":{"count":1},"lists":{"groups":[{"type":"created","count":2,"items":[]}]},"homeCity":"Mexico City, 09","bio":"","contact":{}},{"id":"10372496","firstName":"Alberto","lastName":"Fernández Huertas","gender":"male","photo":{"prefix":"https:\/\/igx.4sqi.net\/img\/user\/","suffix":"\/10372496-NUUZ31ETBRUR0403.jpg"},"tips":{"count":0},"lists":{"groups":[{"type":"created","count":5,"items":[]}]},"homeCity":"Barcelona, Espanya","bio":"","contact":{"twitter":"albertofdzhuer","facebook":"1267393818"}},{"id":"51769816","firstName":"Vanessa","lastName":"Martínez Pérez","gender":"female","photo":{"prefix":"https:\/\/igx.4sqi.net\/img\/user\/","suffix":"\/NTRF25QDTKWC0PHD.jpg"},"tips":{"count":0},"lists":{"groups":[{"type":"created","count":2,"items":[]}]},"homeCity":"Barcelona, 56","bio":"","contact":{"facebook":"1286528487"}},{"id":"4935515","firstName":"David","lastName":"Gómez Rios","gender":"male","photo":{"prefix":"https:\/\/igx.4sqi.net\/img\/user\/","suffix":"\/1EWNSYLM2J4A0VSK.jpg"},"tips":{"count":6},"lists":{"groups":[{"type":"created","count":2,"items":[]}]},"homeCity":"Rubí, Espanya","bio":"","contact":{"twitter":"david_goriver","facebook":"1152392334"}},{"id":"5470184","firstName":"Jordi","lastName":"Ferreras Jerez","gender":"male","photo":{"prefix":"https:\/\/igx.4sqi.net\/img\/user\/","suffix":"\/TDOHWZJ2HMQMMJED.jpg"},"tips":{"count":1},"lists":{"groups":[{"type":"created","count":2,"items":[]}]},"homeCity":"Sabadell, Espanya","bio":"","contact":{}},{"id":"28505082","firstName":"Karon","lastName":"Lynn","gender":"male","photo":{"prefix":"https:\/\/igx.4sqi.net\/img\/user\/","suffix":"\/TUQZ200KGPGEXTBE.jpg"},"tips":{"count":0},"lists":{"groups":[{"type":"created","count":2,"items":[]}]},"homeCity":"North Hollywood, CA","bio":"Professional Dancer\/Choreographer in LA from NYC. I teach every Monday & Friday 4:30PM Millennium Dance Complex","contact":{"twitter":"karonalynn","facebook":"612901301"}},{"id":"3733749","firstName":"Marta","lastName":"Hutesà","gender":"female","photo":{"prefix":"https:\/\/igx.4sqi.net\/img\/user\/","suffix":"\/3733749-ZPAOIGPKLCKXT0K5.jpg"},"tips":{"count":116},"lists":{"groups":[{"type":"created","count":21,"items":[]}]},"homeCity":"Barcelona, Spain","bio":"","contact":{"twitter":"martahutesa","facebook":"1418498332"}},{"id":"34678737","firstName":"Bernat","lastName":"Ortiz Rabella","gender":"male","photo":{"prefix":"https:\/\/igx.4sqi.net\/img\/user\/","suffix":"\/blank_boy.png","default":true},"tips":{"count":0},"lists":{"groups":[{"type":"created","count":2,"items":[]}]},"homeCity":"Cataluña","bio":"","contact":{"facebook":"521473127"}}]}]},"tips":{"count":4},"homeCity":"Cataluña","bio":"","contact":{"facebook":"664937091"},"photos":{"count":3,"items":[{"id":"5253ec0c11d2dcd2258800b3","createdAt":1381231628,"source":{"name":"Foursquare for iOS","url":"https:\/\/foursquare.com\/download\/#\/iphone"},"prefix":"https:\/\/igx.4sqi.net\/img\/general\/","suffix":"\/44772003_khn3dev9m5B-WonMttCBfYx54m26jEtMbDAnSD2BGk0.jpg","width":720,"height":960,"visibility":"public","venue":{"id":"4bee533de24d20a156d47214","name":"Platja de Sant Joan","contact":{},"location":{"address":"Carrer del Mar","lat":41.46572392392854,"lng":2.28090763092041,"labeledLatLngs":[{"label":"display","lat":41.46572392392854,"lng":2.28090763092041}],"postalCode":"08390","cc":"ES","city":"Montgat","state":"Cataluña","country":"España","formattedAddress":["Carrer del Mar","08390 Montgat Cataluña"]},"categories":[{"id":"4bf58dd8d48988d1e2941735","name":"Beach","pluralName":"Beaches","shortName":"Beach","icon":{"prefix":"https:\/\/ss3.4sqi.net\/img\/categories_v2\/parks_outdoors\/beach_","suffix":".png"},"primary":true}],"verified":false,"stats":{"tipCount":18,"usersCount":1144,"checkinsCount":2091},"like":false,"beenHere":{"lastCheckinExpiredAt":0}}}]},"checkinPings":"off","pings":false,"type":"user","mayorships":{"count":0,"items":[]},"checkins":{"count":144,"items":[]},"lists":{"count":6,"groups":[{"type":"created","count":2,"items":[{"id":"5153447ae4b0431b5b7d05d0","name":"Comidas","description":"","editable":false,"public":true,"collaborative":false,"url":"\/user\/44772003\/list\/comidas","canonicalUrl":"https:\/\/foursquare.com\/user\/44772003\/list\/comidas","createdAt":1364411514,"updatedAt":1387656086,"followers":{"count":0},"listItems":{"count":11}},{"id":"50e210fbe4b0c6dcd0956c52","name":"Shopping","description":"","editable":false,"public":true,"collaborative":false,"url":"\/user\/44772003\/list\/shopping","canonicalUrl":"https:\/\/foursquare.com\/user\/44772003\/list\/shopping","createdAt":1356992763,"updatedAt":1356992766,"followers":{"count":0},"listItems":{"count":1}}]},{"type":"followed","count":2,"items":[]},{"type":"yours","count":2,"items":[{"id":"44772003\/todos","name":"Marta's Saved Places","description":"","type":"todos","editable":false,"public":true,"collaborative":false,"url":"\/user\/44772003\/list\/todos","canonicalUrl":"https:\/\/foursquare.com\/user\/44772003\/list\/todos","listItems":{"count":1}},{"id":"44772003\/venuelikes","name":"Marta\u2019s Liked Places","description":"","type":"likes","editable":false,"public":true,"collaborative":false,"url":"\/user\/44772003\/list\/venuelikes","canonicalUrl":"https:\/\/foursquare.com\/user\/44772003\/list\/venuelikes","listItems":{"count":0}}]}]},"blockedStatus":"none","lenses":[]}}}