{"meta":{"code":200,"requestId":"5b53f8b3f594df1ecb7eed90"},"notifications":[{"type":"notificationTray","item":{"unreadCount":0}}],"response":{"user":{"id":"458907","firstName":"Carlos 🇲🇽","lastName":"Trevez","gender":"male","canonicalUrl":"https:\/\/foursquare.com\/ronnytheeuwes","photo":{"prefix":"https:\/\/igx.4sqi.net\/img\/user\/","suffix":"\/YNMGLYAP3ZTFCJ4S.jpg"},"friends":{"count":57,"groups":[{"type":"friends","name":"Mutual friends","count":0,"items":[]},{"type":"others","name":"Other friends","count":57,"items":[{"id":"6698531","firstName":"Sarah Famke","lastName":"Oortgijsen","gender":"female","photo":{"prefix":"https:\/\/igx.4sqi.net\/img\/user\/","suffix":"\/6698531-C4UF3INDC5XYBAS5.jpg"},"tips":{"count":5},"lists":{"groups":[{"type":"created","count":2,"items":[]}]},"homeCity":"Amsterdam, Nederland","bio":"","contact":{"facebook":"1677860635576712"}},{"id":"24265930","firstName":"Frossja","lastName":"Drieman","gender":"female","photo":{"prefix":"https:\/\/igx.4sqi.net\/img\/user\/","suffix":"\/RPOUZT1NSQ5VIT2Z.jpg"},"tips":{"count":0},"lists":{"groups":[{"type":"created","count":2,"items":[]}]},"homeCity":"Halfweg","bio":"","contact":{"facebook":"1070281584"}},{"id":"90101948","firstName":"Haroon","lastName":"Ali","gender":"male","photo":{"prefix":"https:\/\/igx.4sqi.net\/img\/user\/","suffix":"\/90101948-F5FSPWBX3UDRYJ2M.jpg"},"tips":{"count":1},"lists":{"groups":[{"type":"created","count":2,"items":[]}]},"homeCity":"Amsterdam, North Holland","bio":"","contact":{"facebook":"100003645593326"}},{"id":"13722276","firstName":"Saskia","lastName":"Pique","gender":"female","photo":{"prefix":"https:\/\/igx.4sqi.net\/img\/user\/","suffix":"\/FAVWH0I4UY1DQZXK.jpg"},"tips":{"count":0},"lists":{"groups":[{"type":"created","count":2,"items":[]}]},"homeCity":"Rotterdam, Nederland","bio":"","contact":{"twitter":"saskiapique","facebook":"1045552590"}},{"id":"86240918","firstName":"Erik","lastName":"Vonfleet","gender":"male","photo":{"prefix":"https:\/\/igx.4sqi.net\/img\/user\/","suffix":"\/86240918-H1QTIPR3OIGXCS41.jpg"},"tips":{"count":0},"lists":{"groups":[{"type":"created","count":3,"items":[]}]},"homeCity":"Nijmegen, Gelderland","bio":"","contact":{}},{"id":"81633474","firstName":"Stijn","lastName":"Thomaes","gender":"male","photo":{"prefix":"https:\/\/igx.4sqi.net\/img\/user\/","suffix":"\/81633474-KOWXHONYQWT2HLEE.jpg"},"tips":{"count":0},"lists":{"groups":[{"type":"created","count":2,"items":[]}]},"homeCity":"Deventer, Overijssel","bio":"","contact":{}},{"id":"11341333","firstName":"Buzz","lastName":"Aldrin","gender":"male","photo":{"prefix":"https:\/\/igx.4sqi.net\/img\/user\/","suffix":"\/ESHOBSAABMQDRJUJ.jpg"},"tips":{"count":10},"lists":{"groups":[{"type":"created","count":2,"items":[]}]},"homeCity":"Amsterdam, Nederland","bio":"","contact":{}},{"id":"56312752","firstName":"Thijs","lastName":"Klaassen","gender":"none","photo":{"prefix":"https:\/\/igx.4sqi.net\/img\/user\/","suffix":"\/LOQLXHT3XKZHJ1WW.jpg"},"tips":{"count":0},"lists":{"groups":[{"type":"created","count":2,"items":[]}]},"homeCity":"Amsterdam, 07","bio":"","contact":{}},{"id":"53778570","firstName":"Petra","lastName":"Feijs","gender":"female","photo":{"prefix":"https:\/\/igx.4sqi.net\/img\/user\/","suffix":"\/NTLADZPUDLPRJ00A.jpg"},"tips":{"count":0},"lists":{"groups":[{"type":"created","count":2,"items":[]}]},"homeCity":"Kerkrade","bio":"","contact":{"facebook":"593559658"}},{"id":"38032017","firstName":"Orlando","lastName":"Praag","gender":"male","photo":{"prefix":"https:\/\/igx.4sqi.net\/img\/user\/","suffix":"\/SDOZQNMMW0ZJSFQC.jpg"},"tips":{"count":0},"lists":{"groups":[{"type":"created","count":2,"items":[]}]},"homeCity":"Noord-Holland","bio":"","contact":{"facebook":"690612002"}}]}]},"tips":{"count":115},"homeCity":"Rotterdam","bio":"Producer, Film Buff, DJ @ Roffa","contact":{"twitter":"ronnytheeuwes"},"photos":{"count":481,"items":[{"id":"5b4c715b0a464d003315ee13","createdAt":1531736411,"source":{"name":"Swarm for iOS","url":"https:\/\/www.swarmapp.com"},"prefix":"https:\/\/igx.4sqi.net\/img\/general\/","suffix":"\/458907_259T8BRcGgx_pcTX952uml7G_gJLOXxoikJpo3UV3Oc.jpg","width":1280,"height":1920,"visibility":"public","venue":{"id":"4ab65230f964a520947620e3","name":"LantarenVenster","contact":{"phone":"+31102772277","formattedPhone":"+31 10 277 2277","twitter":"lantarenvenster","facebook":"108201265870022","facebookUsername":"LantarenVenster","facebookName":"LantarenVenster"},"location":{"address":"Otto Reuchlinweg 996","lat":51.90489883396685,"lng":4.487035211366009,"labeledLatLngs":[{"label":"display","lat":51.90489883396685,"lng":4.487035211366009}],"postalCode":"3072 MD","cc":"NL","city":"Rotterdam","state":"Zuid-Holland","country":"Nederland","formattedAddress":["Otto Reuchlinweg 996","3072 MD Rotterdam","Nederland"]},"categories":[{"id":"4bf58dd8d48988d17f941735","name":"Movie Theater","pluralName":"Movie Theaters","shortName":"Movie Theater","icon":{"prefix":"https:\/\/ss3.4sqi.net\/img\/categories_v2\/arts_entertainment\/movietheater_","suffix":".png"},"primary":true}],"verified":true,"stats":{"tipCount":53,"usersCount":2375,"checkinsCount":7030},"url":"http:\/\/www.lantarenvenster.nl","like":false,"allowMenuUrlEdit":true,"beenHere":{"lastCheckinExpiredAt":0}}}]},"checkinPings":"off","pings":false,"type":"user","mayorships":{"count":0,"items":[]},"checkins":{"count":10803,"items":[]},"lists":{"count":32,"groups":[{"type":"created","count":10,"items":[{"id":"4f795918e4b087957c65b4b0","name":"Amsterdam <3","description":"Great little and big places in Amsterdam, personal fav's","editable":false,"public":true,"collaborative":false,"url":"\/ronnytheeuwes\/list\/amsterdam-3","canonicalUrl":"https:\/\/foursquare.com\/ronnytheeuwes\/list\/amsterdam-3","createdAt":1333352728,"updatedAt":1523384081,"photo":{"id":"4e9f3e1982310652a7c1bd98","createdAt":1319058969,"prefix":"https:\/\/igx.4sqi.net\/img\/general\/","suffix":"\/32YBJSQG2FQVSAZUZRDLL3NEWQ31H2NJVWRATCKWVSPXK5XF.jpg","width":720,"height":540,"user":{"id":"7116656","firstName":"Harmen","lastName":"Sijsma","gender":"male","photo":{"prefix":"https:\/\/igx.4sqi.net\/img\/user\/","suffix":"\/CHEHHPD54GFVTMAH.jpg"}},"visibility":"public"},"followers":{"count":14},"listItems":{"count":140}},{"id":"527d032b11d2b7c4ce0a4752","name":"Rotterdam <3","description":"","editable":false,"public":true,"collaborative":false,"url":"\/ronnytheeuwes\/list\/rotterdam-3","canonicalUrl":"https:\/\/foursquare.com\/ronnytheeuwes\/list\/rotterdam-3","createdAt":1383924523,"updatedAt":1436955144,"photo":{"id":"527a9d3011d2e112ed00375f","createdAt":1383767344,"prefix":"https:\/\/igx.4sqi.net\/img\/general\/","suffix":"\/23741576_52VqAdnOSbXxLlboD6CL8cGMDJeyRput7WJgd4rjAyY.jpg","width":960,"height":720,"user":{"id":"23741576","firstName":"Nikita","lastName":"Stolyarov","gender":"male","photo":{"prefix":"https:\/\/igx.4sqi.net\/img\/user\/","suffix":"\/HYZPPXCX3FDG3RH4.jpg"}},"visibility":"public"},"followers":{"count":0},"listItems":{"count":106}},{"id":"52de829211d2aa61d9521f1a","name":"Haarlem <3","description":"","editable":false,"public":true,"collaborative":false,"url":"\/ronnytheeuwes\/list\/haarlem-3","canonicalUrl":"https:\/\/foursquare.com\/ronnytheeuwes\/list\/haarlem-3","createdAt":1390314130,"updatedAt":1436955071,"photo":{"id":"520d025f11d2f5de5c01fd27","createdAt":1376584287,"prefix":"https:\/\/igx.4sqi.net\/img\/general\/","suffix":"\/698892_0bC9BuoDwJOiHWCOmusRqCKdOPdxjSXburYX-gFKLf4.jpg","width":960,"height":720,"user":{"id":"698892","firstName":"Tom","lastName":"H","gender":"male","photo":{"prefix":"https:\/\/igx.4sqi.net\/img\/user\/","suffix":"\/FJONJRQ53MDC0ZHS.jpg"}},"visibility":"public"},"followers":{"count":0},"listItems":{"count":36}}]},{"type":"followed","count":20,"items":[]},{"type":"yours","count":2,"items":[{"id":"458907\/todos","name":"Carlos 🇲🇽's Saved Places","description":"","type":"todos","editable":false,"public":true,"collaborative":false,"url":"\/ronnytheeuwes\/list\/todos","canonicalUrl":"https:\/\/foursquare.com\/ronnytheeuwes\/list\/todos","listItems":{"count":12}},{"id":"458907\/venuelikes","name":"Carlos 🇲🇽\u2019s Liked Places","description":"","type":"likes","editable":false,"public":true,"collaborative":false,"url":"\/ronnytheeuwes\/list\/venuelikes","canonicalUrl":"https:\/\/foursquare.com\/ronnytheeuwes\/list\/venuelikes","listItems":{"count":0}}]}]},"blockedStatus":"none","lenses":[]}}}