{"meta":{"code":200,"requestId":"5b5369eb1ed2194222f1bf15"},"notifications":[{"type":"notificationTray","item":{"unreadCount":0}}],"response":{"user":{"id":"46098197","firstName":"Rita","lastName":"Petrova","gender":"female","canonicalUrl":"https:\/\/foursquare.com\/sagaandesideria","photo":{"prefix":"https:\/\/igx.4sqi.net\/img\/user\/","suffix":"\/46098197-ZUKIW05VVSAA3XB3.jpg"},"friends":{"count":35,"groups":[{"type":"friends","name":"Mutual friends","count":0,"items":[]},{"type":"others","name":"Other friends","count":35,"items":[{"id":"146488509","firstName":"Алина","lastName":"Белая","gender":"female","photo":{"prefix":"https:\/\/igx.4sqi.net\/img\/user\/","suffix":"\/146488509-ER23ZMJY3SE1U4TL.jpg"},"tips":{"count":1},"lists":{"groups":[{"type":"created","count":3,"items":[]}]},"homeCity":"Saint Petersburg, St.-Petersburg","bio":"I am Guybrush Threepwood, mighty art critic!","contact":{"facebook":"1023832881043881"}},{"id":"156143188","firstName":"Андрей","lastName":"Николаев","gender":"male","photo":{"prefix":"https:\/\/igx.4sqi.net\/img\/user\/","suffix":"\/156143188-NK1ZIZ5TGWMQ0WE1.jpg"},"tips":{"count":0},"lists":{"groups":[{"type":"created","count":2,"items":[]}]},"homeCity":"Saint Petersburg, St.-Petersburg","bio":"","contact":{"facebook":"424275321094537"}},{"id":"7698156","firstName":"Andrey","lastName":"Sokolov","gender":"male","photo":{"prefix":"https:\/\/igx.4sqi.net\/img\/user\/","suffix":"\/43FW0RWEMTZCKE4R.jpg"},"tips":{"count":4},"lists":{"groups":[{"type":"created","count":2,"items":[]}]},"homeCity":"Россия","bio":"","contact":{"twitter":"mryoghurt"}},{"id":"9006227","firstName":"Roman","lastName":"Semizarov","gender":"male","photo":{"prefix":"https:\/\/igx.4sqi.net\/img\/user\/","suffix":"\/I5ROZJTJHYW2WDG1.jpg"},"tips":{"count":1},"lists":{"groups":[{"type":"created","count":2,"items":[]}]},"homeCity":"город Санкт-Петербург, Россия","bio":"","contact":{"twitter":"semizarov","facebook":"10153465487569395"}},{"id":"19847479","firstName":"Valery","lastName":"Sizikova","gender":"female","photo":{"prefix":"https:\/\/igx.4sqi.net\/img\/user\/","suffix":"\/19847479-Y4QOIFEJP5OGYQQA.jpg"},"tips":{"count":1},"lists":{"groups":[{"type":"created","count":3,"items":[]}]},"homeCity":"Россия","bio":"","contact":{}},{"id":"130706965","firstName":"Arina","lastName":"Khokhlova","gender":"female","photo":{"prefix":"https:\/\/igx.4sqi.net\/img\/user\/","suffix":"\/130706965-NQQ3C55XHNS5ZLTR.jpg"},"tips":{"count":2},"lists":{"groups":[{"type":"created","count":2,"items":[]}]},"homeCity":"Hersonissos, ESYE43","bio":"","contact":{}},{"id":"32328067","firstName":"Александр","lastName":"Atlas","gender":"male","photo":{"prefix":"https:\/\/igx.4sqi.net\/img\/user\/","suffix":"\/MZ4WOJDDNIKFDROX.jpg"},"tips":{"count":9},"lists":{"groups":[{"type":"created","count":4,"items":[]}]},"homeCity":"Saint-Peterbourg ","bio":"","contact":{"facebook":"796484897065960"}},{"id":"19164057","firstName":"Ilya","lastName":"Lobanov","gender":"male","photo":{"prefix":"https:\/\/igx.4sqi.net\/img\/user\/","suffix":"\/19164057-V5E40GCDKI5Z13JL.jpg"},"tips":{"count":3},"lists":{"groups":[{"type":"created","count":2,"items":[]}]},"homeCity":"Россия","bio":"","contact":{"facebook":"100003260659341"}},{"id":"97878265","firstName":"PAvel","lastName":"Anukhin","gender":"male","photo":{"prefix":"https:\/\/igx.4sqi.net\/img\/user\/","suffix":"\/97878265-VFBYT3RG0Y1X5G4Q.jpg"},"tips":{"count":20},"lists":{"groups":[{"type":"created","count":2,"items":[]}]},"homeCity":"Saint Petersburg, Russia","bio":"","contact":{"twitter":"pavel_anukhin","facebook":"100000768166869"}},{"id":"38253404","firstName":"Al","lastName":"Minin","gender":"male","photo":{"prefix":"https:\/\/igx.4sqi.net\/img\/user\/","suffix":"\/blank_boy.png","default":true},"tips":{"count":0},"lists":{"groups":[{"type":"created","count":2,"items":[]}]},"homeCity":"City of St. Petersburg","bio":"","contact":{}}]}]},"tips":{"count":13},"homeCity":"City of St. Petersburg","bio":"","contact":{"twitter":"sagaandesideria","facebook":"100002904942989"},"photos":{"count":84,"items":[{"id":"5aec99382632ec002ce797de","createdAt":1525455160,"source":{"name":"Swarm for iOS","url":"https:\/\/www.swarmapp.com"},"prefix":"https:\/\/igx.4sqi.net\/img\/general\/","suffix":"\/46098197_0RDmr3Bn1ZYjkVl9zAVMMH1kzRhFVZdX_Rj2squHpEI.jpg","width":1920,"height":1434,"visibility":"public","venue":{"id":"4c040b64187ec928b87fb67b","name":"Venice Beach","contact":{"phone":"+13103996990","formattedPhone":"+1 310-399-6990"},"location":{"address":"Venice Beach","crossStreet":"along the Pacific Ocean","lat":33.987336321900536,"lng":-118.4736366584405,"postalCode":"90291","cc":"US","city":"Venice","state":"CA","country":"United States","formattedAddress":["Venice Beach (along the Pacific Ocean)","Venice, CA 90291","United States"]},"categories":[{"id":"4bf58dd8d48988d1e2941735","name":"Beach","pluralName":"Beaches","shortName":"Beach","icon":{"prefix":"https:\/\/ss3.4sqi.net\/img\/categories_v2\/parks_outdoors\/beach_","suffix":".png"},"primary":true}],"verified":false,"stats":{"tipCount":570,"usersCount":70574,"checkinsCount":116359},"url":"http:\/\/venicebeach.com","like":false,"beenHere":{"lastCheckinExpiredAt":0}}}]},"checkinPings":"off","pings":false,"type":"user","mayorships":{"count":0,"items":[]},"checkins":{"count":3017,"items":[]},"lists":{"count":3,"groups":[{"type":"created","count":1,"items":[{"id":"51c07bc4498eb60532c20c49","name":"summertime","description":"","editable":false,"public":true,"collaborative":false,"url":"\/sagaandesideria\/list\/summertime","canonicalUrl":"https:\/\/foursquare.com\/sagaandesideria\/list\/summertime","createdAt":1371569092,"updatedAt":1389627523,"photo":{"id":"51432515e88961406ec264a0","createdAt":1363354901,"prefix":"https:\/\/igx.4sqi.net\/img\/general\/","suffix":"\/15329174_NRqEwAvXK7myeePno0Bxaj1SDqVdAdxGi9hUXHLPSx4.jpg","width":620,"height":413,"user":{"id":"15329174","firstName":"The Village Петербург","gender":"none","photo":{"prefix":"https:\/\/igx.4sqi.net\/img\/user\/","suffix":"\/EAXNZJXUOJEHCVWT.jpg"},"type":"page"},"visibility":"public"},"followers":{"count":0},"listItems":{"count":10}}]},{"type":"followed","count":0,"items":[]},{"type":"yours","count":2,"items":[{"id":"46098197\/todos","name":"Rita's Saved Places","description":"","type":"todos","editable":false,"public":true,"collaborative":false,"url":"\/sagaandesideria\/list\/todos","canonicalUrl":"https:\/\/foursquare.com\/sagaandesideria\/list\/todos","listItems":{"count":3}},{"id":"46098197\/venuelikes","name":"Rita\u2019s Liked Places","description":"","type":"likes","editable":false,"public":true,"collaborative":false,"url":"\/sagaandesideria\/list\/venuelikes","canonicalUrl":"https:\/\/foursquare.com\/sagaandesideria\/list\/venuelikes","listItems":{"count":0}}]}]},"blockedStatus":"none","lenses":[]}}}