{"meta":{"code":200,"requestId":"5b5416d66a607161ea3076bf"},"notifications":[{"type":"notificationTray","item":{"unreadCount":0}}],"response":{"user":{"id":"99967","firstName":"Ozan","lastName":"Sakin","gender":"male","canonicalUrl":"https:\/\/foursquare.com\/osakin","photo":{"prefix":"https:\/\/igx.4sqi.net\/img\/user\/","suffix":"\/99967-IOIGR5UXUBGKPWHV.jpg"},"friends":{"count":153,"groups":[{"type":"friends","name":"Mutual friends","count":0,"items":[]},{"type":"others","name":"Other friends","count":153,"items":[{"id":"813861","firstName":"Emre","lastName":"Erbirer","gender":"male","photo":{"prefix":"https:\/\/igx.4sqi.net\/img\/user\/","suffix":"\/VZJ1YNLKL0NZN3X4.jpg"},"tips":{"count":16},"lists":{"groups":[{"type":"created","count":2,"items":[]}]},"homeCity":"Erenkoy, İstanbul","bio":"arts & culture, creative industries, marketing pro. freelance daydreamer, joker collector and gym rat. emreerbirer@gmail.com","contact":{"twitter":"emreerbirer","facebook":"100001144540097"}},{"id":"5330136","firstName":"Zeynep","lastName":"B","gender":"female","photo":{"prefix":"https:\/\/igx.4sqi.net\/img\/user\/","suffix":"\/5330136-T0BWDMCIXROET43G.jpg"},"tips":{"count":42},"lists":{"groups":[{"type":"created","count":7,"items":[]}]},"homeCity":"Dubai, United Arab Emirates","bio":"","contact":{}},{"id":"1967739","firstName":"bediz","lastName":"Yildirim","gender":"female","photo":{"prefix":"https:\/\/igx.4sqi.net\/img\/user\/","suffix":"\/1967739-WOHD1SD504VARM4B.jpg"},"tips":{"count":0},"lists":{"groups":[{"type":"created","count":2,"items":[]}]},"homeCity":"Istanbul, Türkiye","bio":"","contact":{"twitter":"bediz_"}},{"id":"47207201","firstName":"Ayça","lastName":"Su","gender":"female","photo":{"prefix":"https:\/\/igx.4sqi.net\/img\/user\/","suffix":"\/47207201-NDZOW43JGCX45PGQ.jpg"},"tips":{"count":5},"lists":{"groups":[{"type":"created","count":2,"items":[]}]},"homeCity":"Istanbul","bio":"","contact":{}},{"id":"2792283","firstName":"Şafak","lastName":"Otur","gender":"male","photo":{"prefix":"https:\/\/igx.4sqi.net\/img\/user\/","suffix":"\/2792283_KI0YOAC6_MIpqrGF0D_h_GnGFhtRPs6qSofkL0poaaGUcH13dJiMbBzawJcuJtQ0hS9a4Vyjt.jpg"},"tips":{"count":172},"lists":{"groups":[{"type":"created","count":7,"items":[]}]},"homeCity":"Istanbul, Türkiye","bio":"Designer & Developer","contact":{"twitter":"safakotur","facebook":"1502200945"}},{"id":"92625984","firstName":"Muzaffer","lastName":"Ergişi","gender":"male","photo":{"prefix":"https:\/\/igx.4sqi.net\/img\/user\/","suffix":"\/92625984_OCKtkXNA_OGZukr7lH0gJm6K4ShAQlMGYsx3U0kkKjuamSJSKsb9_-uXlNjjyNz_4ZopBje_Y.jpg"},"tips":{"count":0},"lists":{"groups":[{"type":"created","count":2,"items":[]}]},"homeCity":"Abidinpasa, Ankara, Turkey","bio":"","contact":{"twitter":"herseybosbea","facebook":"100002909797194"}},{"id":"94705644","firstName":"Şeyma","lastName":"Eyce","gender":"female","photo":{"prefix":"https:\/\/igx.4sqi.net\/img\/user\/","suffix":"\/94705644_G2aJ8yUe__kskVU8FCXx854QyctqL-zpZIEBBp41AFMNQiA_XeUiKyPnevkof7dgFPVsGhXXT.jpg"},"tips":{"count":0},"lists":{"groups":[{"type":"created","count":2,"items":[]}]},"homeCity":"Istanbul","bio":"","contact":{"twitter":"eyceseyma","facebook":"100006032238869"}},{"id":"14750848","firstName":"Pinar","lastName":"Guneri","gender":"female","photo":{"prefix":"https:\/\/igx.4sqi.net\/img\/user\/","suffix":"\/14750848-LQUB3XKC0BRN3GUE.jpg"},"tips":{"count":13},"lists":{"groups":[{"type":"created","count":2,"items":[]}]},"homeCity":"Istanbul, Türkiye","bio":"","contact":{"twitter":"pinarguneri"}},{"id":"172569497","firstName":"Nurbanu","lastName":"Ergen","gender":"female","photo":{"prefix":"https:\/\/igx.4sqi.net\/img\/user\/","suffix":"\/172569497-WUMU0NF3SOT5U5TK"},"tips":{"count":0},"lists":{"groups":[{"type":"created","count":2,"items":[]}]},"homeCity":"Istanbul, 34","bio":"","contact":{}},{"id":"172092329","firstName":"Edanur","lastName":"Övey","gender":"female","photo":{"prefix":"https:\/\/igx.4sqi.net\/img\/user\/","suffix":"\/172092329-MSQ1H4FF02EBQ4B5"},"tips":{"count":0},"lists":{"groups":[{"type":"created","count":2,"items":[]}]},"homeCity":"Istanbul, 34","bio":"","contact":{}}]}]},"tips":{"count":200},"homeCity":"İstanbul","bio":"İstanbul'da check-in yapmak hiç zevkli değil.","contact":{"twitter":"osakin","facebook":"10152504202747765"},"photos":{"count":506,"items":[{"id":"5908205b75cb8c4818977b7f","createdAt":1493704795,"source":{"name":"Swarm for iOS","url":"https:\/\/www.swarmapp.com"},"prefix":"https:\/\/igx.4sqi.net\/img\/general\/","suffix":"\/99967_vrI5NSgqkyrWNXd9wvs_8rSC2oEAr781jyb16ZeOHAc.jpg","width":1440,"height":1920,"visibility":"public","venue":{"id":"4b6d99b8f964a5203e7f2ce3","name":"International Terminal (国際線ターミナル)","contact":{"phone":"+81357578111","formattedPhone":"+81 3-5757-8111","facebook":"416746601679596","facebookUsername":"TokyoInternationalAirTerminal","facebookName":"羽田空港国際線旅客ターミナル／Tokyo International Air Terminal"},"location":{"address":"羽田空港2-6-5","lat":35.54500740266884,"lng":139.76898908615112,"labeledLatLngs":[{"label":"display","lat":35.54500740266884,"lng":139.76898908615112}],"postalCode":"144-0041","cc":"JP","city":"東京","state":"東京都","country":"日本","formattedAddress":["羽田空港2-6-5","大田区, 東京都","144-0041","日本"]},"categories":[{"id":"4bf58dd8d48988d1eb931735","name":"Airport Terminal","pluralName":"Airport Terminals","shortName":"Terminal","icon":{"prefix":"https:\/\/ss3.4sqi.net\/img\/categories_v2\/travel\/airport_gate_","suffix":".png"},"primary":true}],"verified":false,"stats":{"tipCount":243,"usersCount":68772,"checkinsCount":186126},"url":"http:\/\/www.haneda-airport.jp\/inter\/","like":false,"venueRatingBlacklisted":true,"beenHere":{"lastCheckinExpiredAt":0}}}]},"checkinPings":"off","pings":false,"type":"user","mayorships":{"count":0,"items":[]},"checkins":{"count":4081,"items":[]},"lists":{"count":25,"groups":[{"type":"created","count":17,"items":[{"id":"5aa10e4516ef676f8cb83cac","name":"Tokyo Ebisu","description":"","editable":false,"public":true,"collaborative":false,"url":"\/osakin\/list\/tokyo-ebisu","canonicalUrl":"https:\/\/foursquare.com\/osakin\/list\/tokyo-ebisu","createdAt":1520504389,"updatedAt":1520918873,"photo":{"id":"4f915912e4b09d834fe7ee85","createdAt":1334925586,"prefix":"https:\/\/igx.4sqi.net\/img\/general\/","suffix":"\/Ux6joT13GangLwxicU_ITMB-DcUst77W0ACJRve0wBM.jpg","width":720,"height":537,"user":{"id":"8400685","firstName":"Yuji","lastName":"Watanabe","gender":"male","photo":{"prefix":"https:\/\/igx.4sqi.net\/img\/user\/","suffix":"\/NM4B22HCUI1JUQVI.jpg"}},"visibility":"public"},"followers":{"count":0},"listItems":{"count":3}},{"id":"5aa169c00d8a0f69cc7829fb","name":"Tokyo Sushi","description":"","editable":false,"public":true,"collaborative":false,"url":"\/osakin\/list\/tokyo-sushi","canonicalUrl":"https:\/\/foursquare.com\/osakin\/list\/tokyo-sushi","createdAt":1520527808,"updatedAt":1520533473,"photo":{"id":"4f59af86e4b0ecd60665a39e","createdAt":1331277702,"prefix":"https:\/\/igx.4sqi.net\/img\/general\/","suffix":"\/F7p789vjeKZQNfjMRgEUixM0cjhpIP-96x56gHY3rTo.jpg","width":537,"height":720,"user":{"id":"20923635","firstName":"Midori","lastName":"Watano","gender":"female","photo":{"prefix":"https:\/\/igx.4sqi.net\/img\/user\/","suffix":"\/BG30X2YTTBKQNYAH.jpg"}},"visibility":"public"},"followers":{"count":0},"listItems":{"count":7}},{"id":"5a5530c74186866612df1f5c","name":"Çakal Lezzetler Beşiktaş","description":"","editable":false,"public":true,"collaborative":false,"url":"\/osakin\/list\/%C3%A7akal-lezzetler-be%C5%9Fikta%C5%9F","canonicalUrl":"https:\/\/foursquare.com\/osakin\/list\/%C3%A7akal-lezzetler-be%C5%9Fikta%C5%9F","createdAt":1515532487,"updatedAt":1515532610,"followers":{"count":0},"listItems":{"count":7}}]},{"type":"followed","count":6,"items":[]},{"type":"yours","count":2,"items":[{"id":"99967\/todos","name":"Ozan's Saved Places","description":"","type":"todos","editable":false,"public":true,"collaborative":false,"url":"\/osakin\/list\/todos","canonicalUrl":"https:\/\/foursquare.com\/osakin\/list\/todos","listItems":{"count":93}},{"id":"99967\/venuelikes","name":"Ozan\u2019s Liked Places","description":"","type":"likes","editable":false,"public":true,"collaborative":false,"url":"\/osakin\/list\/venuelikes","canonicalUrl":"https:\/\/foursquare.com\/osakin\/list\/venuelikes","listItems":{"count":0}}]}]},"blockedStatus":"none","lenses":[]}}}